{
  "user": [
    {
      "email": "pareek.np1@gmail.com",
      "firstName": "Nidhish",
      "lastName": "Pareek",
      "mobileNumber": "9509336954",
      "id": 1
    },
    {
      "email": "nidhish.pareek@gmail.com",
      "firstName": "Nidhish 2",
      "lastName": "Pareek 2",
      "mobileNumber": "8696861773",
      "id": 2
    },
    {
      "email": "par@sd.com",
      "firstName": "fsf",
      "lastName": "fasfs",
      "mobileNumber": 8696861773,
      "id": 3
    },
    {
      "email": "p@a.com",
      "firstName": "f",
      "lastName": "sfs",
      "mobileNumber": 8696861773,
      "id": 4
    }
  ]
}